algokit/__init__.py
algokit/__main__.py
algokit/cli/__init__.py
algokit/cli/codespace.py
algokit/cli/common/__init__.py
algokit/cli/common/constants.py
algokit/cli/common/utils.py
algokit/cli/compile.py
algokit/cli/compilers/__init__.py
algokit/cli/compilers/python.py
algokit/cli/compilers/typescript.py
algokit/cli/completions.py
algokit/cli/config.py
algokit/cli/dispenser.py
algokit/cli/doctor.py
algokit/cli/explore.py
algokit/cli/generate.py
algokit/cli/goal.py
algokit/cli/init/__init__.py
algokit/cli/init/command.py
algokit/cli/init/example.py
algokit/cli/init/helpers.py
algokit/cli/localnet.py
algokit/cli/project/__init__.py
algokit/cli/project/bootstrap.py
algokit/cli/project/deploy.py
algokit/cli/project/link.py
algokit/cli/project/list.py
algokit/cli/project/run.py
algokit/cli/task.py
algokit/cli/tasks/__init__.py
algokit/cli/tasks/analyze.py
algokit/cli/tasks/assets.py
algokit/cli/tasks/ipfs.py
algokit/cli/tasks/mint.py
algokit/cli/tasks/nfd.py
algokit/cli/tasks/send_transaction.py
algokit/cli/tasks/sign_transaction.py
algokit/cli/tasks/transfer.py
algokit/cli/tasks/utils.py
algokit/cli/tasks/vanity_address.py
algokit/cli/tasks/wallet.py
algokit/cli/tui/__init__.py
algokit/cli/tui/init/__init__.py
algokit/cli/tui/init/example_selector.py
algokit/cli/tui/init/screens/__init__.py
algokit/cli/tui/init/screens/example_selector_screen.py
algokit/core/__init__.py
algokit/core/_toml.py
algokit/core/_vendor/__init__.py
algokit/core/_vendor/auth0/__init__.py
algokit/core/_vendor/auth0/authentication/__init__.py
algokit/core/_vendor/auth0/authentication/token_verifier.py
algokit/core/atomic_write.py
algokit/core/codespace.py
algokit/core/compilers/python.py
algokit/core/compilers/typescript.py
algokit/core/conf.py
algokit/core/config_commands/__init__.py
algokit/core/config_commands/container_engine.py
algokit/core/config_commands/js_package_manager.py
algokit/core/config_commands/py_package_manager.py
algokit/core/config_commands/version_prompt.py
algokit-2.10.1.dist-info/METADATA
algokit-2.10.1.dist-info/WHEEL
algokit-2.10.1.dist-info/entry_points.txt
algokit-2.10.1.dist-info/licenses/LICENSE
algokit-2.10.1.dist-info/RECORD
