Metadata-Version: 2.4
Name: algokit
Version: 2.10.1
Summary: Algorand development kit command-line interface
License: MIT
License-File: LICENSE
Author: Algorand Foundation
Author-email: contact@algorand.foundation
Requires-Python: >=3.10,<3.15
Classifier: License :: OSI Approved :: MIT License
Classifier: Programming Language :: Python :: 3
Classifier: Programming Language :: Python :: 3.10
Classifier: Programming Language :: Python :: 3.11
Classifier: Programming Language :: Python :: 3.12
Classifier: Programming Language :: Python :: 3.13
Classifier: Programming Language :: Python :: 3.14
Requires-Dist: algokit-utils (>=4.0.1,<5.0.0)
Requires-Dist: click (==8.1.8)
Requires-Dist: copier (>=9.11.3,<10.0.0)
Requires-Dist: cryptography (>=44.0.2,<45.0.0)
Requires-Dist: httpx (>=0.23.1,<=0.28.1)
Requires-Dist: jsondiff (>=2.0.0,<3.0.0)
Requires-Dist: keyring (==25.6.0)
Requires-Dist: mslex (>=1.1.0,<2.0.0)
Requires-Dist: multiformats (==0.3.1)
Requires-Dist: multiformats_config (==0.3.1)
Requires-Dist: prompt_toolkit (==3.0.51)
Requires-Dist: pyclip (>=0.7.0,<0.8.0)
Requires-Dist: pyjwt (>=2.10.1,<3.0.0)
Requires-Dist: python-dotenv (>=1.0.0,<2.0.0)
Requires-Dist: pywin32 (>=311,<312) ; sys_platform == "win32"
Requires-Dist: questionary (>=1.10.0,<2.0.0)
Requires-Dist: requests (>=2.31.0,<3.0.0)
Requires-Dist: shellingham (>=1.5.4,<2.0.0)
Requires-Dist: textual (>=3.0.1,<4.0.0)
Requires-Dist: tomli (>=2.0.1,<3.0.0) ; python_version < "3.11"
